winpwn/__init__.py
winpwn/context.py
winpwn/dbg.py
winpwn/misc.py
winpwn/var.py
winpwn/win.py
winpwn/winpwn.py
jitpwn-0.0.1.dist-info/METADATA
jitpwn-0.0.1.dist-info/WHEEL
jitpwn-0.0.1.dist-info/top_level.txt
jitpwn-0.0.1.dist-info/RECORD
